fourtwonine/__init__.py
fourtwonine/_core.py
fourtwonine/_headers.py
fourtwonine/_utils.py
fourtwonine/config.py
fourtwonine/datastructures.py
fourtwonine/errors.py
fourtwonine/fastapi.py
fourtwonine/limiter.py
fourtwonine/middleware.py
fourtwonine/py.typed
fourtwonine-0.1.0.dist-info/METADATA
fourtwonine-0.1.0.dist-info/WHEEL
fourtwonine-0.1.0.dist-info/RECORD
